{
  "username": "Mi Max Turbo",
  "modulo": "5-3-2",
  "capitano": "ZAPATA D.",
  "vicecapitano": "SCAMACCA",
  "slots": {
    "1": "MERET",
    "2": "DI LORENZO",
    "3": "EBOSSE",
    "4": "GABBIA",
    "5": "GASPAR K.",
    "6": "VALLE",
    "7": "SAMARDZIC",
    "8": "THORSTVEDT",
    "9": "FAZZINI",
    "10": "SCAMACCA",
    "11": "ZAPATA D.",
    "12": "MILINKOVIC-SAVIC V.",
    "13": "CONTINI",
    "14": "OPENDA",
    "15": "ASLLANI",
    "16": "TRAMONI M.",
    "17": "NZOLA",
    "18": "SAELEMAEKERS",
    "19": "CONCEICAO",
    "20": "STANCIU",
    "21": "CASTRO S.",
    "22": "CAMBIASO",
    "23": ""
  },
  "saved_at": "2025-09-05T21:09:56.529Z"
}